[
  {
    "command": "shutdown /s /t 0",
    "name": "1 Shutdown now"
  },
  {
    "command": "rundll32.exe user32.dll,LockWorkStation",
    "name": "2 Lock Screen"
  },
  {
    "command": "rundll32.exe powrprof.dll,SetSuspendState 0,1,0",
    "name": "3 Suspend"
  },
  {
    "command": "start powershell -command C:\\Development\\KDEConnectCommands\\KDE-Commands-Windows\\batchFiles\\open_steam.bat",
    "name": "4 Start steam"
  },
  {
    "command": "start powershell -command C:\\Development\\KDEConnectCommands\\KDE-Commands-Windows\\batchFiles\\kill_steam.bat",
    "name": "5 Exit steam"
  },
  {
    "command": "start powershell -command C:\\Development\\KDEConnectCommands\\KDE-Commands-Windows\\batchFiles\\brave.bat",
    "name": "6 Start Brave"
  },
  {
    "command": "start powershell -command C:\\Development\\KDEConnectCommands\\KDE-Commands-Windows\\batchFiles\\move_brave.bat",
    "name": "7 Move Brave"
  },
  {
    "command": "start powershell -command C:\\Development\\KDEConnectCommands\\KDE-Commands-Windows\\batchFiles\\kill_brave.bat",
    "name": "8 Exit Brave"
  },
  {
    "command": "start powershell -command C:\\Development\\KDEConnectCommands\\KDE-Commands-Windows\\batchFiles\\dev_environment.bat",
    "name": "9 Development environment"
  }
]
